neet/__init__.py
neet/__main__.py
neet/__version__.py
neet/bed_ops.py
neet/filter.py
neet/helper_functions.py
neet/pileup_extractor.py
neet/poi_sample_comparer.py
neet/poi_summary.py
neet/poi_view.py
neet/summary.py
neet/two_sample_extractor.py
neet/summary_style/__init__.py
neet/summary_style/plotly.js
neet/summary_style/style.css
neet_nanopore-1.0.0.dist-info/LICENSE
neet_nanopore-1.0.0.dist-info/METADATA
neet_nanopore-1.0.0.dist-info/WHEEL
neet_nanopore-1.0.0.dist-info/entry_points.txt
neet_nanopore-1.0.0.dist-info/top_level.txt
neet_nanopore-1.0.0.dist-info/RECORD
