Metadata-Version: 2.1
Name: neet-nanopore
Version: 1.0.0
Home-page: https://github.com/dietvin/neet
Author: Vincent Dietrich
Author-email: dietricv@uni-mainz.de
License: LICENSE
Classifier: Environment :: Console
Classifier: License :: OSI Approved :: GNU General Public License v3 (GPLv3)
Classifier: Programming Language :: Python :: 3
Classifier: Topic :: Scientific/Engineering :: Bio-Informatics
Classifier: Operating System :: OS Independent
Requires-Python: >3.9
License-File: LICENSE
Requires-Dist: plotly ==5.18.0
Requires-Dist: kaleido ==0.2.1
Requires-Dist: numpy ==1.26.2
Requires-Dist: pandas ==2.1.4
Requires-Dist: tqdm ==4.66.1
Requires-Dist: intervaltree ==3.1.0
Requires-Dist: scipy ==1.11.4
Requires-Dist: statsmodels ==0.14.1
Requires-Dist: pyfiglet ==1.0.2
Requires-Dist: setuptools ==69.0.3
